{
  "--bg": "#0A0A14",
  "--surf": "#15151E",
  "--surf2": "#202029",
  "--surf3": "#2C2C34",
  "--bdr": "#44444C",
  "--txt": "#EAE8F5",
  "--mute": "#6A6A8A",
  "--red": "#FFB300",
  "--orange": "#FF8F00",
  "--yellow": "#5C6BC0",
  "--green": "#7986CB",
  "--teal": "#FFD54F",
  "--blue": "#3949AB",
  "--purple": "#FFA000",
  "--pink": "#9FA8DA",
  "--lime": "#FFC107",
  "--kick": "#FF8F00",
  "--snare": "#FFD54F",
  "--hhat": "#9FA8DA",
  "--clap": "#FFB300",
  "--tom1": "#7986CB",
  "--tom2": "#FFA000",
  "--ride": "#283593",
  "--crash": "#5C6BC0",
  "--perc1": "#3949AB",
  "--perc2": "#FFC107",
  "--bass": "#FF8F00",
  "--fx1": "#5C6BC0",
  "--fx2": "#FFD54F",
  "--fx3": "#FFA000",
  "--fx4": "#FFC107",
  "--fx5": "#FFB300"
}